{
  "products": [
    {
      "name": "Processeur Intel Core i9-13900K",
      "price": 579.99,
      "description": "Puissant processeur de 13ème génération avec 24 cœurs et 32 threads. Performance exceptionnelle pour le gaming et le travail professionnel.",
      "image": "https://m.media-amazon.com/images/I/51CsbchCa-L._AC_UF894,1000_QL80_.jpg",
      "stock": 14,
      "category": "Processeurs",
      "rating": 4.8,
      "reviewCount": 3,
      "reviews": [
        {
          "id": "1-r1",
          "author": "Marc D.",
          "rating": 5,
          "comment": "Performances incroyables en montage vidéo et en jeu.",
          "date": "2026-05-12"
        },
        {
          "id": "1-r2",
          "author": "Julie R.",
          "rating": 4,
          "comment": "Très rapide, mais chauffe un peu sans bon refroidissement.",
          "date": "2026-05-09"
        },
        {
          "id": "1-r3",
          "author": "Nicolas T.",
          "rating": 5,
          "comment": "Parfait pour une config haut de gamme.",
          "date": "2026-05-03"
        }
      ],
      "id": "1"
    },
    {
      "name": "ASUS TUF Gaming NVIDIA GeForce RTX™ 4080 Super OC Edition Carte graphique",
      "price": 1299.99,
      "description": "Carte GPU haut de gamme pour le gaming en 4K et le ray tracing. 16 Go de VRAM GDDR6X.",
      "image": "https://m.media-amazon.com/images/I/81rCZZvkIVL._AC_UF894,1000_QL80_.jpg",
      "stock": 8,
      "category": "Cartes Graphiques",
      "rating": 4.7,
      "reviewCount": 3,
      "reviews": [
        {
          "id": "2-r1",
          "author": "Kevin B.",
          "rating": 5,
          "comment": "4K ultra fluide, ray tracing impeccable.",
          "date": "2026-05-15"
        },
        {
          "id": "2-r2",
          "author": "Amine S.",
          "rating": 4,
          "comment": "Très puissante, un peu volumineuse dans le boîtier.",
          "date": "2026-05-06"
        },
        {
          "id": "2-r3",
          "author": "Laura M.",
          "rating": 5,
          "comment": "Silencieuse et stable même en charge.",
          "date": "2026-05-01"
        }
      ],
      "id": "2"
    },
    {
      "name": "RAM Corsair Dominator 32GB DDR5",
      "price": 199.99,
      "description": "Mémoire DDR5 ultra-rapide 6000MHz pour une performance maximale. Kit 32GB (2x16GB).",
      "image": "https://assets.corsair.com/image/upload/c_pad,q_auto,h_1024,w_1024,f_auto/products/Memory/CMT32GX5M2X6400C38/Gallery/DOMINATOR_RGB_PLATINUM_BLACK_DDR5_13.webp",
      "stock": 25,
      "category": "Mémoire",
      "rating": 4.6,
      "reviewCount": 2,
      "reviews": [
        {
          "id": "3-r1",
          "author": "Pierre L.",
          "rating": 5,
          "comment": "Stable en XMP, super look RGB.",
          "date": "2026-05-11"
        },
        {
          "id": "3-r2",
          "author": "Sabrina C.",
          "rating": 4,
          "comment": "Très bonne RAM, installation facile.",
          "date": "2026-05-04"
        }
      ],
      "id": "3"
    },
    {
      "name": "SSD NVMe Samsung 990 Pro 2TB",
      "price": 299.99,
      "description": "SSD NVMe ultra-rapide avec vitesses de lecture jusqu'à 7100 MB/s. Parfait pour le gaming et le contenu créatif.",
      "image": "https://m.media-amazon.com/images/I/61qidDdfgRL.jpg",
      "stock": 12,
      "category": "Stockage",
      "rating": 4.9,
      "reviewCount": 3,
      "reviews": [
        {
          "id": "4-r1",
          "author": "Thomas E.",
          "rating": 5,
          "comment": "Démarrage système ultra rapide.",
          "date": "2026-05-14"
        },
        {
          "id": "4-r2",
          "author": "Élise P.",
          "rating": 5,
          "comment": "Excellent pour les gros projets Adobe.",
          "date": "2026-05-07"
        },
        {
          "id": "4-r3",
          "author": "Hugo V.",
          "rating": 4,
          "comment": "Très rapide, prix un peu élevé.",
          "date": "2026-05-02"
        }
      ],
      "id": "4"
    },
    {
      "name": "Boîtier NZXT H7 Flow",
      "price": 159.99,
      "description": "Boîtier ATX spacieux avec excellent flux d'air et panneaux en verre trempé. Gestion des câbles optimisée.",
      "image": "https://m.media-amazon.com/images/I/51hN4NaXj2L._AC_UF894,1000_QL80_.jpg",
      "stock": 20,
      "category": "Boîtiers",
      "rating": 4.5,
      "reviewCount": 2,
      "reviews": [
        {
          "id": "5-r1",
          "author": "Damien F.",
          "rating": 5,
          "comment": "Très bon airflow et montage agréable.",
          "date": "2026-05-08"
        },
        {
          "id": "5-r2",
          "author": "Inès G.",
          "rating": 4,
          "comment": "Beau design, filtres faciles à nettoyer.",
          "date": "2026-05-01"
        }
      ],
      "id": "5"
    },
    {
      "name": "Alimentation Corsair HX1200 Platinum",
      "price": 229.99,
      "description": "Alimentation 1200W certifiée Platinum avec rendement 92%. Parfaite pour les systèmes haute performance.",
      "image": "https://www.dadducharger.com/cdn/shop/files/4.webp?v=1761314813",
      "stock": 18,
      "category": "Alimentations",
      "rating": 4.7,
      "reviewCount": 2,
      "reviews": [
        {
          "id": "6-r1",
          "author": "Yanis K.",
          "rating": 5,
          "comment": "Très stable, aucun souci sur une config RTX 4080.",
          "date": "2026-05-13"
        },
        {
          "id": "6-r2",
          "author": "Camille N.",
          "rating": 4,
          "comment": "Excellente alimentation, câbles un peu rigides.",
          "date": "2026-05-05"
        }
      ],
      "id": "6"
    },
    {
      "name": "Refroidisseur Noctua NH-D15S",
      "price": 99.99,
      "description": "Refroidisseur air performant avec deux ventilateurs silencieux. Excellent rapport performance/bruit.",
      "image": "https://m.media-amazon.com/images/I/81Fz3KKzEJL.jpg",
      "stock": 30,
      "category": "Refroidissement",
      "rating": 4.8,
      "reviewCount": 2,
      "reviews": [
        {
          "id": "7-r1",
          "author": "Romain A.",
          "rating": 5,
          "comment": "Ultra silencieux, températures excellentes.",
          "date": "2026-05-10"
        },
        {
          "id": "7-r2",
          "author": "Mélanie Z.",
          "rating": 4,
          "comment": "Très efficace, installation un peu longue.",
          "date": "2026-05-02"
        }
      ],
      "id": "7"
    },
    {
      "name": "Carte Mère ASUS ROG Strix Z790",
      "price": 349.99,
      "description": "Carte mère haut de gamme avec socket LGA1700 pour processeurs Intel 13ème génération. Support WiFi 6E.",
      "image": "https://dlcdnwebimgs.asus.com/files/media/9A827026-9AD2-4CE7-9958-DB583A2DB6F8/v1/img/kv/ROG-Strix-Z790-E-Gaming.png",
      "stock": 10,
      "category": "Cartes Mères",
      "rating": 4.6,
      "reviewCount": 2,
      "reviews": [
        {
          "id": "8-r1",
          "author": "Benoît Q.",
          "rating": 5,
          "comment": "BIOS complet et très bonnes performances.",
          "date": "2026-05-16"
        },
        {
          "id": "8-r2",
          "author": "Sarah O.",
          "rating": 4,
          "comment": "Très bonne carte, mais chère.",
          "date": "2026-05-06"
        }
      ],
      "id": "8"
    },
    {
      "name": "asd",
      "price": 123,
      "description": "asd",
      "image": "asd",
      "stock": 23,
      "category": "Processeurs",
      "rating": 3.5,
      "reviewCount": 2,
      "reviews": [
        {
          "id": "EF9q9i7iDs0-r1",
          "author": "Utilisateur 1",
          "rating": 4,
          "comment": "Produit correct pour le prix.",
          "date": "2026-05-20"
        },
        {
          "id": "EF9q9i7iDs0-r2",
          "author": "Utilisateur 2",
          "rating": 3,
          "comment": "Fait le travail, sans plus.",
          "date": "2026-05-20"
        }
      ],
      "createdAt": "2026-05-20T13:33:26.353Z",
      "id": "EF9q9i7iDs0"
    }
  ],
  "users": [
    {
      "id": "1",
      "name": "Admin",
      "email": "admin@techgear.com"
    }
  ],
  "$schema": "./node_modules/json-server/schema.json"
}